{
    "Форма": {
        "1": "Треугольная колба",
        "2": "Сферическая колба",
        "3": "Мензурка",
        "4": "Флакон",
        "5": "Квадратная банка",
        "6": "Круглая банка",
        "7": "Бутылочка",
        "8": "Пузырек",
        "9": "Бутылка",
        "10": "Овальная бутылка",
        "11": "Фигурный флакон",
        "12": "Фляжка"
    },
    "Материал": {
        "1": "Стекло",
        "2": "Стекло",
        "3": "Стекло",
        "4": "Камень",
        "5": "Магически лед",
        "6": "Магическая энергия",
        "7": "Кость",
        "8": "Фарфор",
        "9": "Кожа",
        "10": "Кристалл",
        "11": "Металл",
        "12": "Благородный металл"
    },
    "Крышка": {
        "1": "Пробка",
        "2": "Каучук",
        "3": "Воск",
        "4": "Металл",
        "5": "Закручивающаяся",
        "6": "Магическая печать"
    },
    "Цвет": {
        "1": "Белый",
        "2": "Красный",
        "3": "Оранжевый",
        "4": "Желтый",
        "5": "Зеленый",
        "6": "Синий",
        "7": "Фиолетовый",
        "8": "Золотой",
        "9": "Серебряный",
        "10": "Разноцветный"
    },
    "Интенсивность запаха": {
        "1": "Едва уловимый",
        "2": "Легкий",
        "3": "Слабый",
        "4": "Слабый",
        "5": "Приглушенный",
        "6": "Сильный",
        "7": "Сильный",
        "8": "Резкий",
        "9": "Густой",
        "10": "Сбивающий с ног"
    },
    "Запах": {
        "1": "Сладковатый",
        "2": "Пряный",
        "3": "Терпкий",
        "4": "Смолистый",
        "5": "Мускусный",
        "6": "Вонючий",
        "7": "Эфирный",
        "8": "Цветочный",
        "9": "Мятный",
        "10": "Ореховый",
        "11": "Цитрусовый",
        "12": "Озоновый"
    },
    "Вкус": {
        "1": "Садкий",
        "2": "Кислый",
        "3": "Соленый",
        "4": "Горький",
        "5": "Острый",
        "6": "Вяжущий"
    },
    "Типы ингридиентов": {
        "1": "Минералы",
        "2": "Алхимические элементы",
        "3": "Алхимические элементы",
        "4": "Растительные",
        "5": "Растительные",
        "6": "Животные",
        "7": "Животные",
        "8": "Сверхъестественные"
    },
    "Минералы": {
        "1": "Купорос",
        "2": "Натрий",
        "3": "Ртуть",
        "4": "Сера",
        "5": "Селитра",
        "6": "Сурьма"
    },
    "Алхимические элементы": {
        "1": "Красная тинктура",
        "2": "Киноварь",
        "3": "Антимония",
        "4": "Амальгама",
        "5": "Витриоль",
        "6": "Земляное масло"
    },
    "Растительные": {
        "1": "Лист",
        "2": "Корень",
        "3": "Сок/Масло",
        "4": "Семена",
        "5": "Цветок",
        "6": "Кора"
    },
    "Животные": {
        "1": "Кость",
        "2": "Волос",
        "3": "Перо",
        "4": "Коготь",
        "5": "Зуб",
        "6": "Кровь/Желчь"
    },
    "Сверхъестественные": {
        "1": "Святая вода",
        "2": "Святая вода",
        "3": "Превосходный клей",
        "4": "Эктоплазма",
        "5": "Эктоплазма",
        "6": "Другой эликсир"
    },
    "Реакция": {
        "1": "Растворение в спирте",
        "2": "Растворение в спирте",
        "3": "Насыщение магической энергией",
        "4": "Насыщение магической энергией",
        "5": "Прокаливание",
        "6": "Прокаливание",
        "7": "Коагуляция",
        "8": "Разложение",
        "9": "Дисциляция",
        "10": "Дисциляция",
        "11": "Возгонка",
        "12": "Возгонка",
        "13": "Фильтрация",
        "14": "Фильтрация",
        "15": "Ферментация",
        "16": "Кипячение",
        "17": "Кипячение",
        "18": "Плавление",
        "19": "Замораживание",
        "20": "Конденсация"
    }
}